birchrest/__init__.py
birchrest/cli.py
birchrest/version.py
birchrest/__boilerplate__/README.md
birchrest/__boilerplate__/__birch__.py
birchrest/__boilerplate__/src/__init__.py
birchrest/__boilerplate__/src/main.py
birchrest/__boilerplate__/src/controllers/__init__.py
birchrest/__boilerplate__/src/controllers/hello_controller.py
birchrest/__boilerplate__/tests/test_hello.py
birchrest/app/__init__.py
birchrest/app/birchrest_app.py
birchrest/decorators/__init__.py
birchrest/decorators/body.py
birchrest/decorators/controller.py
birchrest/decorators/delete.py
birchrest/decorators/get.py
birchrest/decorators/head.py
birchrest/decorators/middleware.py
birchrest/decorators/options.py
birchrest/decorators/params.py
birchrest/decorators/patch.py
birchrest/decorators/post.py
birchrest/decorators/produces.py
birchrest/decorators/protected.py
birchrest/decorators/put.py
birchrest/decorators/queries.py
birchrest/decorators/tag.py
birchrest/exceptions/__init__.py
birchrest/exceptions/api_error.py
birchrest/exceptions/invalid_controller_registration.py
birchrest/exceptions/invalid_validation_model.py
birchrest/exceptions/missing_auth_handler_error.py
birchrest/http/__init__.py
birchrest/http/request.py
birchrest/http/response.py
birchrest/http/server.py
birchrest/http/status.py
birchrest/middlewares/__init__.py
birchrest/middlewares/cors.py
birchrest/middlewares/logger.py
birchrest/middlewares/middleware.py
birchrest/middlewares/rate_limiter.py
birchrest/openapi/__init__.py
birchrest/openapi/dataclass_to_model.py
birchrest/openapi/route_to_model.py
birchrest/routes/__init__.py
birchrest/routes/controller.py
birchrest/routes/route.py
birchrest/routes/validator.py
birchrest/types/__init__.py
birchrest/types/types.py
birchrest/unittest/__init__.py
birchrest/unittest/birchrest_test_case.py
birchrest/unittest/test_adapter.py
birchrest/utils/__init__.py
birchrest/utils/artwork.py
birchrest/utils/dict_to_dataclass.py
birchrest/utils/logger.py
birchrest-1.1.0.dist-info/LICENSE
birchrest-1.1.0.dist-info/METADATA
birchrest-1.1.0.dist-info/WHEEL
birchrest-1.1.0.dist-info/entry_points.txt
birchrest-1.1.0.dist-info/top_level.txt
birchrest-1.1.0.dist-info/RECORD
