Metadata-Version: 2.1
Name: birchrest
Version: 1.1.0
Summary: A lightweight Python framework for building REST APIs with a controller-based approach. It includes built-in middleware, error handling, auth handling, automatic response management and more.
Author-email: Alexander Engström <alexander@engstrom.ae>
License: MIT
Project-URL: homepage, https://alexandengstrom.github.io/birchrest
Project-URL: repository, https://github.com/alexandengstrom/birchrest
Project-URL: documentation, https://alexandengstrom.github.io/birchrest
Project-URL: issues, https://github.com/alexandengstrom/birchrest/issues
Project-URL: changelog, https://github.com/alexandengstrom/birchrest/releases
Keywords: api,rest,framework,web,microservices,controller,middleware,auth management,response handling,fastapi alternative,flask alternative,restful api,python web framework
Classifier: Development Status :: 4 - Beta
Classifier: Intended Audience :: Developers
Classifier: Topic :: Software Development :: Libraries :: Application Frameworks
Classifier: License :: OSI Approved :: MIT License
Classifier: Programming Language :: Python :: 3
Classifier: Programming Language :: Python :: 3.8
Classifier: Programming Language :: Python :: 3.9
Classifier: Programming Language :: Python :: 3.10
Classifier: Programming Language :: Python :: 3.11
Classifier: Programming Language :: Python :: 3.12
Classifier: Operating System :: OS Independent
Classifier: Environment :: Web Environment
Classifier: Typing :: Typed
Classifier: Framework :: AsyncIO
Classifier: Topic :: Internet :: WWW/HTTP :: HTTP Servers
Requires-Python: >=3.8
License-File: LICENSE
Requires-Dist: colorama
